ckd/__init__.py
ckd/config.py
ckd/data.py
ckd/evaluate.py
ckd/main.py
ckd/predict.py
ckd/preprocess.py
ckd/utils.py
ckd/files/data/X_test_preprocessed.csv
ckd/files/data/X_test_raw.csv
ckd/files/data/X_train_preprocessed.csv
ckd/files/data/X_train_raw.csv
ckd/files/data/chronic_kidney_disease.arff
ckd/files/data/chronic_kidney_disease.info.txt
ckd/files/data/chronic_kidney_disease_full.arff
ckd/files/data/ckd_raw.csv
ckd/files/data/y_test.csv
ckd/files/data/y_train.csv
ckd/files/models/lr_clf.pkl
ckd/files/models/mv_imputer.pkl
ckd/files/models/rb_scaler.pkl
ckd/files/models/rf_clf.pkl
ckd-0.1.0.data/scripts/cli.py
ckd-0.1.0.dist-info/LICENSE
ckd-0.1.0.dist-info/METADATA
ckd-0.1.0.dist-info/WHEEL
ckd-0.1.0.dist-info/entry_points.txt
ckd-0.1.0.dist-info/top_level.txt
ckd-0.1.0.dist-info/RECORD
