Metadata-Version: 2.1
Name: ckd
Version: 0.1.0
Summary: A package for Chronic Kidney Desease prediction.
Author: Ani Khachatryan
License-File: LICENSE
Requires-Dist: scikit-learn (==1.2.0)
Requires-Dist: pandas (>=1.5.3)
Requires-Dist: fire (>=0.5.0)
